README.txt
setup.py
dynwidgets/__init__.py
dynwidgets/release.py
dynwidgets/widgets.py
dynwidgets.egg-info/PKG-INFO
dynwidgets.egg-info/SOURCES.txt
dynwidgets.egg-info/dependency_links.txt
dynwidgets.egg-info/entry_points.txt
dynwidgets.egg-info/not-zip-safe
dynwidgets.egg-info/requires.txt
dynwidgets.egg-info/top_level.txt
dynwidgets/static/css/appendable_form_field_list.css
dynwidgets/static/images/bin_empty.png
dynwidgets/static/javascript/appendable_form_field_list-source.js
dynwidgets/static/javascript/appendable_form_field_list.js
dynwidgets/templates/__init__.py
