Metadata-Version: 1.0
Name: dynwidgets
Version: 1.1
Summary: TurboGears widget to automatically replicate a list of other widgets (or a FieldSet or ...), including 'add' and 'remove' buttons
Home-page: http://tnr.homeip.net:8081/
Author: Jorge Godoy
Author-email: jgodoy@gmail.com
License: MIT
Keywords: turbogears.widgets
Platform: UNKNOWN
Classifier: Development Status :: 3 - Alpha
Classifier: Operating System :: OS Independent
Classifier: Programming Language :: Python
Classifier: Topic :: Software Development :: Libraries :: Python Modules
Classifier: Framework :: TurboGears
Classifier: Framework :: TurboGears :: Widgets
